fsLogger/__init__.py
fsLogger/abcs.py
fsLogger/filter.py
fsLogger/globHandler.py
fsLogger/globalLocker.py
fsLogger/levels.py
fsLogger/logger.py
fsLogger/loggerManager.py
fsLogger/modules.py
fsLogger/py.typed
python_fslogger-0.2.3.dist-info/LICENSE.md
python_fslogger-0.2.3.dist-info/METADATA
python_fslogger-0.2.3.dist-info/WHEEL
python_fslogger-0.2.3.dist-info/top_level.txt
python_fslogger-0.2.3.dist-info/RECORD
