Metadata-Version: 2.1
Name: python-fslogger
Version: 0.2.3
Summary: Logging utility
Home-page: https://github.com/FusionSolutions/python-fslogger
Author: Andor `iFA` Rajci - Fusions Solutions KFT
Author-email: ifa@fusionsolutions.io
License: GPL-3
Keywords: logging utility fusion solutions fusionsolutions
Classifier: Development Status :: 4 - Beta
Classifier: Topic :: Utilities
Classifier: Programming Language :: Python :: 3 :: Only
Classifier: Programming Language :: Python :: 3.8
Classifier: Programming Language :: Python :: 3.9
Classifier: License :: OSI Approved :: GNU Lesser General Public License v3 or later (LGPLv3+)
Requires-Python: >=3.8.0
License-File: LICENSE.md
